django_transfiles/__init__.py
django_transfiles/admin.py
django_transfiles/apps.py
django_transfiles/models.py
django_transfiles/tests.py
django_transfiles/utils.py
django_transfiles/views.py
django_transfiles/management/__init__.py
django_transfiles/management/commands/__init__.py
django_transfiles/management/commands/translate.py
django_transfiles/migrations/__init__.py
django_transfiles-0.0.2.dist-info/METADATA
django_transfiles-0.0.2.dist-info/WHEEL
django_transfiles-0.0.2.dist-info/top_level.txt
django_transfiles-0.0.2.dist-info/RECORD
