Metadata-Version: 2.1
Name: django-transfiles
Version: 0.0.2
Summary: Translate your django templates easily
Home-page: https://github.com/neiderruiz/django_transfiles
Author: Neider Ruiz
Author-email: contact@neiderruiz.com
License: MIT
Platform: UNKNOWN
Classifier: Development Status :: 3 - Alpha
Classifier: Intended Audience :: Developers
Classifier: License :: OSI Approved :: MIT License
Classifier: Programming Language :: Python :: 3
Classifier: Programming Language :: Python :: 3.7
Classifier: Programming Language :: Python :: 3.8
Classifier: Programming Language :: Python :: 3.9
Classifier: Programming Language :: Python :: 3.10
Classifier: Framework :: Django
Classifier: Framework :: Django :: 3.0
Classifier: Framework :: Django :: 3.1
Classifier: Framework :: Django :: 3.2
Requires-Python: >=3.7
Requires-Dist: Django>=3.0
Requires-Dist: polib>=1.2.0
